LICENSE
yawl/__init__.py
yawl/clients/__init__.py
yawl/clients/bigquery.py
yawl/clients/bigquery_datatransfer.py
yawl/examples/main.py
yawl/examples/sql_files/example.sql
yawl/shared/__init__.py
yawl/shared/constants.py
yawl/workflows/__init__.py
yawl/workflows/base.py
yawl/workflows/bigquery_workflow.py
yawl/workflows/queue.py
yawl-0.1.1.dist-info/LICENSE
yawl-0.1.1.dist-info/WHEEL
yawl-0.1.1.dist-info/METADATA
yawl-0.1.1.dist-info/RECORD
